tfimgsort/__init__.py
tfimgsort/__main__.py
tfimgsort/tfimgsort.py
tfimgsort/tfutil.py
tfimgsort/util.py
tfimgtools-0.0.6.dist-info/DESCRIPTION.rst
tfimgtools-0.0.6.dist-info/METADATA
tfimgtools-0.0.6.dist-info/RECORD
tfimgtools-0.0.6.dist-info/WHEEL
tfimgtools-0.0.6.dist-info/entry_points.txt
tfimgtools-0.0.6.dist-info/metadata.json
tfimgtools-0.0.6.dist-info/top_level.txt
