Metadata-Version: 2.0
Name: tfimgtools
Version: 0.0.6
Summary: A tool for sorting images given a tensorflow model.
Home-page: https://github.com/lukejduncan/tfimgtools
Author: Luke Duncan
Author-email: lukejduncan@gmail.com
License: MIT
Platform: UNKNOWN
Classifier: License :: OSI Approved :: MIT License
Classifier: Development Status :: 1 - Planning
Classifier: Environment :: Console
Classifier: Intended Audience :: Developers
Classifier: Intended Audience :: End Users/Desktop
Classifier: License :: Other/Proprietary License
Classifier: Programming Language :: Python :: 3 :: Only
Classifier: Topic :: Multimedia :: Graphics
Classifier: Topic :: Utilities
Requires-Dist: tensorflow
